LICENSE
MANIFEST.in
README.md
README.rst
setup.py
bin/viewm
viewm/VERSION
viewm/main.py
viewm.egg-info/PKG-INFO
viewm.egg-info/SOURCES.txt
viewm.egg-info/dependency_links.txt
viewm.egg-info/requires.txt
viewm.egg-info/top_level.txt