Metadata-Version: 1.1
Name: viewm
Version: 0.0.1
Summary: Visualization of functional modules to aid biological interpretation of genomes.
Home-page: http://pypi.python.org/pypi/viewm/
Author: Donovan Parks
Author-email: donovan.parks@gmail.com
License: GPLv3
Platform: UNKNOWN
Classifier: Development Status :: 4 - Beta
Classifier: License :: OSI Approved :: GNU General Public License v3 (GPLv3)
Classifier: Natural Language :: English
Classifier: Programming Language :: Python :: 2.7
Classifier: Programming Language :: Python :: 3
Classifier: Topic :: Scientific/Engineering :: Bio-Informatics
